odoo/addons/sale_order_line_source_pricelist/README.rst
odoo/addons/sale_order_line_source_pricelist/__init__.py
odoo/addons/sale_order_line_source_pricelist/__manifest__.py
odoo/addons/sale_order_line_source_pricelist/i18n/es.po
odoo/addons/sale_order_line_source_pricelist/models/__init__.py
odoo/addons/sale_order_line_source_pricelist/models/product_pricelist_item.py
odoo/addons/sale_order_line_source_pricelist/models/sale_order_line.py
odoo/addons/sale_order_line_source_pricelist/readme/CONTRIBUTORS.md
odoo/addons/sale_order_line_source_pricelist/readme/DESCRIPTION.md
odoo/addons/sale_order_line_source_pricelist/readme/USAGE.md
odoo/addons/sale_order_line_source_pricelist/static/description/icon.png
odoo/addons/sale_order_line_source_pricelist/static/description/index.html
odoo/addons/sale_order_line_source_pricelist/tests/__init__.py
odoo/addons/sale_order_line_source_pricelist/tests/test_sale_order_line_source_pricelist.py
odoo/addons/sale_order_line_source_pricelist/views/sale_order_views.xml
odoo_addon_sale_order_line_source_pricelist-17.0.1.0.0.1.dist-info/METADATA
odoo_addon_sale_order_line_source_pricelist-17.0.1.0.0.1.dist-info/WHEEL
odoo_addon_sale_order_line_source_pricelist-17.0.1.0.0.1.dist-info/top_level.txt
odoo_addon_sale_order_line_source_pricelist-17.0.1.0.0.1.dist-info/RECORD
